LICENSE
MANIFEST.in
README.rst
setup.py
jdog/__init__.py
jdog/__main__.py
jdog/cli.py
jdog/jdog.py
jdog/node.py
jdog/parser.py
jdog.egg-info/PKG-INFO
jdog.egg-info/SOURCES.txt
jdog.egg-info/dependency_links.txt
jdog.egg-info/entry_points.txt
jdog.egg-info/not-zip-safe
jdog.egg-info/requires.txt
jdog.egg-info/top_level.txt
jdog/placeholder/__init__.py
jdog/placeholder/faker.py
jdog/placeholder/name.py
jdog/placeholder/option.py
jdog/placeholder/placeholder.py
jdog/placeholder/range.py