Metadata-Version: 1.1
Name: jdog
Version: 1.0.0
Summary: Just another Data Offline Generator
Home-page: https://github.com/petrnymsa/jdog
Author: Petr Nymsa
Author-email: nymsa.petr@outlook.cz
License: MIT
Keywords: data generator,data generation,json scheme,scheme based,cli tool
Platform: UNKNOWN
Classifier: Intended Audience :: Developers
Classifier: License :: OSI Approved :: MIT License
Classifier: Operating System :: POSIX :: Linux
Classifier: Programming Language :: Python
Classifier: Programming Language :: Python :: 3
Classifier: Programming Language :: Python :: 3.6
Classifier: Programming Language :: Python :: 3.7
Classifier: Environment :: Console
Classifier: Topic :: Software Development :: Libraries
